transend/__init__.py
transend/client.py
transend-0.1.1.dist-info/licenses/LICENSE
transend-0.1.1.dist-info/METADATA
transend-0.1.1.dist-info/WHEEL
transend-0.1.1.dist-info/top_level.txt
transend-0.1.1.dist-info/RECORD
