Metadata-Version: 2.4
Name: transend
Version: 0.1.1
Summary: Python Client for the Transend Automotive Tech APIs
Home-page: https://github.com/TranstarIndustries/transend-python
Author: NexaMotion Group / Transtar Industries
Author-email: dev@transtar1.com
Project-URL: Bug Tracker, https://github.com/TranstarIndustries/transend-python/issues
Classifier: Programming Language :: Python :: 3
Classifier: Programming Language :: Python :: 3.8
Classifier: Programming Language :: Python :: 3.9
Classifier: Programming Language :: Python :: 3.10
Classifier: Programming Language :: Python :: 3.11
Classifier: License :: OSI Approved :: MIT License
Classifier: Operating System :: OS Independent
Requires-Python: >=3.8
License-File: LICENSE
Requires-Dist: requests>=2.28.1
Dynamic: author
Dynamic: author-email
Dynamic: classifier
Dynamic: description
Dynamic: description-content-type
Dynamic: home-page
Dynamic: license-file
Dynamic: project-url
Dynamic: requires-dist
Dynamic: requires-python
Dynamic: summary
